README.rst
setup.py
bin/ndb_prop_gen
ndb_prop_gen/__init__.py
ndb_prop_gen/arg.py
ndb_prop_gen/common.py
ndb_prop_gen/error.py
ndb_prop_gen/generator.py
ndb_prop_gen.egg-info/PKG-INFO
ndb_prop_gen.egg-info/SOURCES.txt
ndb_prop_gen.egg-info/dependency_links.txt
ndb_prop_gen.egg-info/top_level.txt