Metadata-Version: 1.1
Name: ndb-prop-gen
Version: 0.0.4
Summary: Google Appengine ndb Property Generator written in python. You can convert json data into your custom ndb property by this library.
Home-page: https://github.com/taxpon/ndb_prop_gen
Author: Takuro Wada
Author-email: taxpon@gmail.com
License: MIT
Platform: UNKNOWN
Classifier: License :: OSI Approved :: MIT License
Classifier: Programming Language :: Python
Classifier: Topic :: Software Development :: Code Generators
